anne/__init__.py
anne/browser/AnneBrowser.py
anne/browser/__init__.py
anne/captcha/AnneCaptcha.py
anne/captcha/__init__.py
anne/info/AnneInfo.py
anne/info/__init__.py
anne/info/data.py
anne/proxy/AnneProxy.py
anne/proxy/__init__.py
anne-1.2.4.dist-info/LICENSE
anne-1.2.4.dist-info/METADATA
anne-1.2.4.dist-info/WHEEL
anne-1.2.4.dist-info/top_level.txt
anne-1.2.4.dist-info/RECORD
