Metadata-Version: 2.1
Name: anne
Version: 1.2.4
Summary: Lib for lazy dev
Home-page: https://github.com/mrship666/anne-lib
Author: AnneHouman
Author-email: annehouman01@gmail.com
License: MIT
Classifier: License :: OSI Approved :: MIT License
Classifier: Programming Language :: Python :: 3.10
Classifier: Operating System :: OS Independent
Requires-Python: >=3.10
License-File: LICENSE
Requires-Dist: bson >=0.5.10
Provides-Extra: dev
Requires-Dist: pytest >=7.0 ; extra == 'dev'
Requires-Dist: twine >=4.0.2 ; extra == 'dev'
